{
  "canonical_id": "ECO-ORG-PROC-011",
  "category": "Organizational",
  "category_code": "ORG",
  "detection": {
    "languages": [
      "org"
    ],
    "method": "hybrid"
  },
  "enabled_by_default": true,
  "family": "Process",
  "family_code": "PROC",
  "id": "ECO-ORG-PROC-011",
  "impact": {
    "confidence": 0.8,
    "notes": "Common in mature orgs too.",
    "type": "cost"
  },
  "layer": "process",
  "legacy_id": "ECO-PROC-011",
  "rationale": "Zombie services are pure waste: cost, risk, and attention.",
  "remediation": {
    "guidance": "Create a decommission playbook and ownership model.",
    "tradeoffs": "Cross-team coordination."
  },
  "severity": "warning",
  "summary": "Without decommissioning, dead systems stay alive and waste resources.",
  "tags": [
    "decommissioning"
  ],
  "tier": 4,
  "title": "No decommissioning workflow",
  "ontology": {
    "system_layers": [
      "process"
    ]
  }
}
